wolf/__init__.py
wolf/cli/__init__.py
wolf/cli/main.py
wolf/core/__init__.py
wolf/core/base.py
wolf/core/logger.py
wolf/modules/__init__.py
wolf/modules/crypto_analysis.py
wolf/modules/csrf.py
wolf/modules/dirbrute.py
wolf/modules/forensics.py
wolf/modules/ipinfo.py
wolf/modules/network_scanner.py
wolf/modules/nslookup.py
wolf/modules/subdomain.py
wolf/modules/threat_intelligence.py
wolf/modules/vulnerability_scanner.py
wolf/modules/web_scanner.py
wolf/modules/wifi.py
wolf/utils/__init__.py
wolf/utils/network.py
wolf/utils/wordlists.py
wolf_cybersecurity_toolkit-0.1.0.dist-info/METADATA
wolf_cybersecurity_toolkit-0.1.0.dist-info/WHEEL
wolf_cybersecurity_toolkit-0.1.0.dist-info/top_level.txt
wolf_cybersecurity_toolkit-0.1.0.dist-info/RECORD
