Metadata-Version: 2.4
Name: wolf-cybersecurity-toolkit
Version: 0.1.0
Summary: A powerful cybersecurity toolkit for Wi-Fi, subdomain, directory attacks, brute-force, CSRF, and more.
Home-page: https://github.com/Tamilselvan-S-Cyber-Security/Wolf-Cybersecurity-Toolkit.git
Author: S. Tamilselvan
Author-email: tamilselvanresearcher@gmail.com
Classifier: Programming Language :: Python :: 3
Classifier: License :: OSI Approved :: MIT License
Classifier: Operating System :: OS Independent
Requires-Python: >=3.6
Requires-Dist: requests
Requires-Dist: scapy
Dynamic: author
Dynamic: author-email
Dynamic: classifier
Dynamic: description
Dynamic: description-content-type
Dynamic: home-page
Dynamic: requires-dist
Dynamic: requires-python
Dynamic: summary
